qtico/__init__.py
qtico/common.py
qtico/install_theme.py
qtico/osx_iconset.py
qtico/py.typed
qtico/qrc_compile.py
qtico/theme_index.py
qtico-0.2.1.dist-info/METADATA
qtico-0.2.1.dist-info/WHEEL
qtico-0.2.1.dist-info/RECORD
