Metadata-Version: 2.4
Name: qtico
Version: 0.2.1
Project-URL: Homepage, http://github.com/flying-sheep/qtico
Author-email: "Philipp A." <flying-sheep@web.de>
License-Expression: GPL-3.0
Keywords: icons,pyqt
Classifier: Development Status :: 4 - Beta
Classifier: Environment :: X11 Applications :: Qt
Classifier: License :: OSI Approved :: GNU General Public License v3 (GPLv3)
Classifier: Programming Language :: Python :: 3 :: Only
Classifier: Programming Language :: Python :: 3.9
Classifier: Programming Language :: Python :: 3.10
Classifier: Programming Language :: Python :: 3.11
Classifier: Programming Language :: Python :: 3.12
Classifier: Programming Language :: Python :: 3.13
Classifier: Topic :: Software Development :: Build Tools
Classifier: Typing :: Typed
Requires-Python: >=3.9
Requires-Dist: qtpy
Provides-Extra: test
Requires-Dist: pytest; extra == 'test'
